{
    "key": "group_6543c3b954be3",
    "title": "Page",
    "fields": [
        {
            "key": "field_6543c3bf0545a",
            "label": "Template",
            "name": "template",
            "type": "select",
            "instructions": "",
            "required": 0,
            "conditional_logic": 0,
            "wrapper": {
                "width": "",
                "class": "",
                "id": ""
            },
            "choices": {
                "default": "Default",
                "home": "Home",
                "gallery": "Gallery"
            },
            "default_value": false,
            "allow_null": 0,
            "multiple": 0,
            "ui": 1,
            "ajax": 0,
            "return_format": "value",
            "placeholder": ""
        }
    ],
    "location": [
        [
            {
                "param": "post_type",
                "operator": "==",
                "value": "page"
            }
        ]
    ],
    "menu_order": 0,
    "position": "side",
    "style": "default",
    "label_placement": "top",
    "instruction_placement": "label",
    "hide_on_screen": "",
    "active": true,
    "description": "",
    "modified": 1698939934
}